covertable/__init__.py
covertable/exceptions.py
covertable/main.py
covertable/criteria/__init__.py
covertable/criteria/greedy.py
covertable/criteria/simple.py
covertable/sorters/__init__.py
covertable/sorters/hash.py
covertable/sorters/random.py
covertable-2.1.0.dist-info/METADATA
covertable-2.1.0.dist-info/WHEEL
covertable-2.1.0.dist-info/top_level.txt
covertable-2.1.0.dist-info/RECORD
