Metadata-Version: 2.1
Name: covertable
Version: 2.1.0
Summary: A flexible pairwise tool written in Python.
Home-page: https://github.com/walkframe/covertable/
Author: righ
Author-email: righ.m9@gmail.com
License: Apache Software License
Keywords: allpair,all-pair,allpairs,all-pairs,pairwise,N-wise,2-wise,3-wise,two-wise,three-wise,N-term,2-term,3-term,two-term,three-term,pairs,pair,combinatorial,covering-array,covering-arrays,pict
Classifier: Intended Audience :: Developers
Classifier: Intended Audience :: Information Technology
Classifier: Intended Audience :: Manufacturing
Classifier: Intended Audience :: Science/Research
Classifier: License :: OSI Approved :: Apache Software License
Classifier: Programming Language :: Python
Classifier: Topic :: Software Development
